mopidy_radionet/__init__.py
mopidy_radionet/backend.py
mopidy_radionet/ext.conf
mopidy_radionet/library.py
mopidy_radionet/radionet.py
Mopidy_RadioNet-0.2.2.dist-info/LICENSE
Mopidy_RadioNet-0.2.2.dist-info/METADATA
Mopidy_RadioNet-0.2.2.dist-info/WHEEL
Mopidy_RadioNet-0.2.2.dist-info/entry_points.txt
Mopidy_RadioNet-0.2.2.dist-info/top_level.txt
Mopidy_RadioNet-0.2.2.dist-info/RECORD
