Metadata-Version: 2.1
Name: Mopidy-RadioNet
Version: 0.2.2
Summary: Mopidy extension for radio.net
Home-page: https://github.com/plintx/mopidy-radionet
Author: plintx
Author-email: mariusz@intx.pl
License: Apache License, Version 2.0
Platform: UNKNOWN
Classifier: Environment :: No Input/Output (Daemon)
Classifier: Intended Audience :: End Users/Desktop
Classifier: License :: OSI Approved :: Apache Software License
Classifier: Operating System :: OS Independent
Classifier: Programming Language :: Python :: 3
Classifier: Programming Language :: Python :: 3.7
Classifier: Topic :: Multimedia :: Sound/Audio :: Players
Requires-Python: >= 3.7
Requires-Dist: Mopidy (>=3.0.0)
Requires-Dist: Pykka (>=2.0.1)
Requires-Dist: setuptools
Requires-Dist: uritools (>=1.0)
